es_hvcc_sensors-0.2.1.data/scripts/hvcc
es_hvcc_sensors-0.2.1.data/scripts/hvutil
hvcc/__init__.py
hvcc/utils.py
hvcc/core/__init__.py
hvcc/core/hv2ir/BufferPool.py
hvcc/core/hv2ir/Connection.py
hvcc/core/hv2ir/HIrConvolution.py
hvcc/core/hv2ir/HIrInlet.py
hvcc/core/hv2ir/HIrLorenz.py
hvcc/core/hv2ir/HIrOutlet.py
hvcc/core/hv2ir/HIrPack.py
hvcc/core/hv2ir/HIrReceive.py
hvcc/core/hv2ir/HIrSend.py
hvcc/core/hv2ir/HIrSwitchcase.py
hvcc/core/hv2ir/HIrTabhead.py
hvcc/core/hv2ir/HIrTabread.py
hvcc/core/hv2ir/HIrTabwrite.py
hvcc/core/hv2ir/HLangAdc.py
hvcc/core/hv2ir/HLangBinop.py
hvcc/core/hv2ir/HLangBiquad.py
hvcc/core/hv2ir/HLangDac.py
hvcc/core/hv2ir/HLangDelay.py
hvcc/core/hv2ir/HLangIf.py
hvcc/core/hv2ir/HLangLine.py
hvcc/core/hv2ir/HLangMessage.py
hvcc/core/hv2ir/HLangNoise.py
hvcc/core/hv2ir/HLangPhasor.py
hvcc/core/hv2ir/HLangPrint.py
hvcc/core/hv2ir/HLangRandom.py
hvcc/core/hv2ir/HLangReceive.py
hvcc/core/hv2ir/HLangSend.py
hvcc/core/hv2ir/HLangSequence.py
hvcc/core/hv2ir/HLangSlice.py
hvcc/core/hv2ir/HLangSystem.py
hvcc/core/hv2ir/HLangTable.py
hvcc/core/hv2ir/HLangUnop.py
hvcc/core/hv2ir/HLangVar.py
hvcc/core/hv2ir/HLangVario.py
hvcc/core/hv2ir/HeavyException.py
hvcc/core/hv2ir/HeavyGraph.py
hvcc/core/hv2ir/HeavyIrObject.py
hvcc/core/hv2ir/HeavyLangObject.py
hvcc/core/hv2ir/HeavyParser.py
hvcc/core/hv2ir/LocalVars.py
hvcc/core/hv2ir/__init__.py
hvcc/core/hv2ir/hv2ir.py
hvcc/core/json/heavy.ir.json
hvcc/core/json/heavy.lang.json
hvcc/generators/__init__.py
hvcc/generators/buildjson/__init__.py
hvcc/generators/buildjson/buildjson.py
hvcc/generators/c2bela/SETUP.md
hvcc/generators/c2bela/__init__.py
hvcc/generators/c2bela/c2bela.py
hvcc/generators/c2bela/templates/linux/Makefile
hvcc/generators/c2daisy/__init__.py
hvcc/generators/c2daisy/c2daisy.py
hvcc/generators/c2daisy/parameters.py
hvcc/generators/c2daisy/static/README.md
hvcc/generators/c2daisy/templates/HeavyDaisy.cpp
hvcc/generators/c2daisy/templates/Makefile
hvcc/generators/c2dpf/__init__.py
es_hvcc_sensors-0.2.1.dist-info/LICENSE
es_hvcc_sensors-0.2.1.dist-info/METADATA
es_hvcc_sensors-0.2.1.dist-info/WHEEL
es_hvcc_sensors-0.2.1.dist-info/top_level.txt
es_hvcc_sensors-0.2.1.dist-info/RECORD
