Metadata-Version: 2.1
Name: es-hvcc-sensors
Version: 0.2.1
Summary: `hvcc` is a python-based dataflow audio programming language compiler that generates C/C++ code and a variety of specific framework wrappers.
Home-page: https://github.com/CorvusPrudens/hvcc
Author: Enzien Audio, Wasted Audio, Electrosmith
License: GPLv3
Platform: UNKNOWN
Classifier: Development Status :: 3 - Alpha
Classifier: Intended Audience :: Developers
Classifier: Topic :: Software Development :: Compilers
Classifier: License :: OSI Approved :: GNU General Public License v3 (GPLv3)
Classifier: Programming Language :: Python :: 3.7
Classifier: Programming Language :: Python :: 3.8
Classifier: Programming Language :: Python :: 3.9
Requires-Python: >=3.7
License-File: LICENSE
Requires-Dist: Jinja2 (>=2.11)
Requires-Dist: importlib-resources (>=5.1)
Requires-Dist: json2daisy (>=0.3.13)
